nailplot.py
nailplot-10.0.3.dist-info/METADATA
nailplot-10.0.3.dist-info/WHEEL
nailplot-10.0.3.dist-info/top_level.txt
nailplot-10.0.3.dist-info/RECORD
