Metadata-Version: 2.1
Name: nailplot
Version: 10.0.3
Requires-Dist: requests
Requires-Dist: google
Requires-Dist: google.generativeai
